Metadata-Version: 1.1
Name: sphinxcontrib-cheader
Version: 1.0.0
Summary: Sphinx c:header directive
Home-page: http://bitbucket.org/birkenfeld/sphinx-contrib
Author: Arto Bendiken
Author-email: arto@bendiken.net
License: Public Domain
Download-URL: http://pypi.python.org/pypi/sphinxcontrib-cheader
Platform: any
Classifier: Development Status :: 5 - Production/Stable
Classifier: Environment :: Console
Classifier: Environment :: Web Environment
Classifier: Intended Audience :: Developers
Classifier: License :: Public Domain
Classifier: Operating System :: OS Independent
Classifier: Programming Language :: Python
Classifier: Topic :: Documentation
Classifier: Topic :: Utilities
